data_memory.v
module data_memory (
    input wire clk,               // Clock
    input wire mem_write,        // Habilita escrita
    input wire [31:0] address,   // Endereço de memória
    input wire [31:0] write_data, // Dado a ser escrito
    output reg [31:0] read_data   // Dado lido
);
    reg [31:0] mem [0:255]; // 256 palavras de 32 bits

    initial begin
        // Inicializa a memória com valores em BINÁRIO
        mem[0] = 32'b00000000000000000000000000000101; // 5
        mem[1] = 32'b00000000000000000000000000001010; // 10
        mem[2] = 32'b00000000000000000000000000001111; // 15
        // Preenche o resto com zeros
        for (integer i = 3; i < 256; i = i + 1) begin
            mem[i] = 32'b00000000000000000000000000000000;
        end
    end

    always @(*) begin
        read_data = mem[address[31:2]];     // Lê o dado da memória
    end

    always @(posedge clk) begin
        if (mem_write) begin
            mem[address[31:2]] <= write_data;    // Escreve o dado na memória
        end
    end

endmodule

alu.v
`timescale 1ns / 1ps

module alu (
    input wire [31:0] a,           // Operando A (vindo do ALU)
    input wire [31:0] b,           // Operando B (vindo do MUX: registrador ou immediate)
    input wire [3:0]  alu_control, // Sinal de controle que define a operação (vem do Controle da ALU)
    output reg [31:0] result,      // Resultado da operação
    output wire       zero         // Flag Zero (1 se result == 0)
);

    // Sempre recalcule o resultado quando qualquer operando ou sinal de controle mudar
    always @(*) begin
        case (alu_control)
            4'b0000: result = a + b;           // ADD
            4'b0001: result = a - b;           // SUB
            4'b0010: result = a & b;           // AND
            4'b0011: result = a | b;           // OR
            4'b0100: result = a ^ b;           // XOR
            4'b0101: result = a << b[4:0];     // SLL. b[4:0] é o shamt (shift amount).
            default: result = 32'b0;           // Operação padrão (resultado zero) para evitar latch
        endcase
    end

    // A flag ZERO é ativada só se o resultado for zero.
    // É uma atribuição contínua (wire), funciona como um circuito combinacional simples.
    assign zero = (result == 32'b0);

endmodule

alu_control_unit.v
module alu_control_unit (
    input wire [1:0] alu_op,     // Parâmetro de controle da ALU
    input wire [2:0] funct3,
    input wire [6:0] funct7,
    output reg [3:0] alu_control // Para a ALU
);

always @(*) begin
    case (alu_op)
        2'b00: alu_control = 4'b0000; // add (para lw, sw, addi)
        2'b01: alu_control = 4'b0001; // sub (para branch)
        2'b10: begin // Instruções do tipo R
            case (funct3)
                3'b000: alu_control = (funct7 == 7'b0000000) ? 4'b0000 : 4'b0001; // add ou sub
                3'b100: alu_control = 4'b0100; // xor
                3'b001: alu_control = 4'b0101; // sll
                default: alu_control = 4'b0000; // add como padrão
            endcase
        end
        default: alu_control = 4'b0000; // add
    endcase
end

endmodule

control_unit.v
`timescale 1ns / 1ps

module control_unit (
    input wire [6:0] opcode, // Código da operação
    input wire [2:0] funct3, // Código da função
    input wire [6:0] funct7, // Código da função extendido
    output reg reg_write, // Habilita escrita no registrador
    output reg alu_src,   // Seleciona a fonte do segundo operando da ALU
    output reg mem_write, // Habilita escrita na memória
    output reg mem_to_reg, // Seleciona a fonte de dados para o registrador
    output reg branch,    // Habilita o branch
    output reg branch_neq, // Habilita o branch se não for igual
    output reg [1:0] alu_op // Seleciona a operação da ALU
);

// Parâmetros para os opcodes
localparam [6:0] OPCODE_R_TYPE = 7'b0110011; // Tipo R
localparam [6:0] OPCODE_ADD_I  = 7'b0010011; // ADDI
localparam [6:0] OPCODE_LOAD   = 7'b0000011; // LOAD
localparam [6:0] OPCODE_STORE  = 7'b0100011; // STORE
localparam [6:0] OPCODE_BRANCH = 7'b1100011; // BRANCH
localparam [6:0] OPCODE_EBREAK = 7'b1110011; // EBREAK

always @(*) begin
    // Valores padrão
    reg_write = 1'b0; // Habilita escrita no registrador
    alu_src   = 1'b0; // Seleciona a fonte do segundo operando da ALU
    mem_write = 1'b0; // Habilita escrita na memória
    mem_to_reg = 1'b0; // Seleciona a fonte de dados para o registrador
    branch    = 1'b0; // Habilita o branch
    branch_neq = 1'b0; // Habilita o branch se não for igual
    alu_op    = 2'b00; // Seleciona a operação da ALU

    case (opcode)
        OPCODE_R_TYPE: begin  // Tipo R
            reg_write = 1'b1; // Habilita escrita no registrador
            alu_src   = 1'b0; // Seleciona a fonte do segundo operando da ALU
            mem_write = 1'b0; // Habilita escrita na memória
            mem_to_reg = 1'b0; // Seleciona a fonte de dados para o registrador
            branch    = 1'b0; // Habilita o branch
            branch_neq = 1'b0; // Habilita o branch se não for igual
            alu_op    = 2'b10; // Seleciona a operação da ALU
        end

        OPCODE_ADD_I: begin // ADDI
            reg_write = 1'b1; // Habilita escrita no registrador
            alu_src   = 1'b1; // Seleciona a fonte do segundo operando da ALU
            mem_write = 1'b0; // Habilita escrita na memória
            mem_to_reg = 1'b0; // Seleciona a fonte de dados para o registrador
            branch    = 1'b0; // Habilita o branch
            branch_neq = 1'b0; // Habilita o branch se não for igual
            alu_op    = 2'b00; // Seleciona a operação da ALU
        end

        OPCODE_LOAD: begin // lw
            reg_write = 1'b1; // Habilita escrita no registrador
            alu_src   = 1'b1; // Seleciona a fonte do segundo operando da ALU
            mem_write = 1'b0; // Habilita escrita na memória
            mem_to_reg = 1'b1; // Seleciona a fonte de dados para o registrador
            branch    = 1'b0; // Habilita o branch
            branch_neq = 1'b0; // Habilita o branch se não for igual
            alu_op    = 2'b00; // Seleciona a operação da ALU
        end

        OPCODE_STORE: begin // sw
            reg_write = 1'b0; // Desabilita escrita no registrador
            alu_src   = 1'b1; // Seleciona a fonte do segundo operando da ALU
            mem_write = 1'b1; // Habilita escrita na memória
            mem_to_reg = 1'bx; // Não se aplica
            branch    = 1'b0; // Habilita o branch
            branch_neq = 1'b0; // Habilita o branch se não for igual
            alu_op    = 2'b00; // Seleciona a operação da ALU
        end

        OPCODE_BRANCH: begin // Tipo B
            reg_write = 1'b0; // Desabilita escrita no registrador
            alu_src   = 1'b0; // Seleciona a fonte do segundo operando da ALU
            mem_write = 1'b0; // Habilita escrita na memória
            mem_to_reg = 1'bx; // Não se aplica
            alu_op    = 2'b01; // Seleciona a operação da ALU

            case (funct3)   // Verifica o tipo de branch
                3'b000: begin  // BEQ
                    branch = 1'b1; // Habilita o branch
                    branch_neq = 1'b0; // Desabilita o branch se não for igual
                end
                3'b001: begin  // BNE
                    branch = 1'b0; // Desabilita o branch
                    branch_neq = 1'b1; // Habilita o branch se não for igual
                end
                default: begin  // Caso padrão
                    branch = 1'b0; // Desabilita o branch
                    branch_neq = 1'b0; // Desabilita o branch se não for igual
                end
            endcase
        end

        // CASE SEPARADO PARA EBREAK
        OPCODE_EBREAK: begin
            reg_write = 1'b0; // Desabilita escrita no registrador
            alu_src   = 1'b0; // Seleciona a fonte do segundo operando da ALU
            mem_write = 1'b0; // Habilita escrita na memória
            mem_to_reg = 1'b0; // Não se aplica
            branch    = 1'b0; // Habilita o branch
            branch_neq = 1'b0; // Habilita o branch se não for igual
            alu_op    = 2'b00; // Seleciona a operação da ALU
        end

        default: begin  // Caso padrão
            reg_write = 1'b0; // Desabilita escrita no registrador
            alu_src   = 1'b0; // Seleciona a fonte do segundo operando da ALU
            mem_write = 1'b0; // Habilita escrita na memória
            mem_to_reg = 1'b0; // Não se aplica
            branch    = 1'b0; // Habilita o branch
            branch_neq = 1'b0; // Habilita o branch se não for igual
            alu_op    = 2'b00; // Seleciona a operação da ALU
        end
    endcase
end

endmodule

sign_extend.v
module sign_extend (
    input wire [31:0] instruction,  // Instrução a ser estendida
    output reg [31:0] imm_ext      // Imediato estendido
);
    always @(*) begin
        case (instruction[6:0])     // Tipo da instrução
            // Tipo I (addi, lw)
            7'b0010011, 7'b0000011:
                imm_ext = {{20{instruction[31]}}, instruction[31:20]};   // Extensão de sinal para Tipo I
            // Tipo S (sw)
            7'b0100011:
                imm_ext = {{20{instruction[31]}}, instruction[31:25], instruction[11:7]};   // Extensão de sinal para Tipo S
            // Tipo SB (bne)
            7'b1100011:
                imm_ext = {{20{instruction[31]}}, instruction[7], instruction[30:25], instruction[11:8], 1'b0};  // Extensão de sinal para Tipo SB
            default:
                imm_ext = 32'b0;         // Caso padrão
        endcase
    end

endmodule

register_file.v
module register_file (
    input wire clk,                // Clock
    input wire reset,              // Reset
    input wire write_enable,       // Habilita escrita
    input wire [4:0] read_reg1,    // Registrador a ser lido 1
    input wire [4:0] read_reg2,    // Registrador a ser lido 2
    input wire [4:0] write_reg,    // Registrador a ser escrito
    input wire [31:0] write_data,  // Dado a ser escrito
    output wire [31:0] read_data1, // Dado lido do registrador 1
    output wire [31:0] read_data2  // Dado lido do registrador 2
);
    reg [31:0] registers [0:31];    // Banco de registradores

    // Leitura assíncrona
    assign read_data1 = (read_reg1 != 0) ? registers[read_reg1] : 0;     // Registrador 1
    assign read_data2 = (read_reg2 != 0) ? registers[read_reg2] : 0;     // Registrador 2

    // Escrita síncrona
always @(posedge clk or posedge reset) begin
    if (reset) begin
        // Inicializa todos os registradores (exceto x0) para zero
        for (integer i = 1; i < 32; i = i + 1) begin  // Inicializa registradores
            registers[i] <= 32'b0;
        end
    end else if (write_enable && write_reg != 0) begin  // Se habilitado e registrador não for 0
        registers[write_reg] <= write_data;  // Se habilitado e registrador não for 0
    end
end

endmodule

instruction_memory.v
module instruction_memory (
    input wire [31:0] address,     // Endereço da instrução
    output reg [31:0] instruction  // Instrução lida
);
    reg [31:0] mem [0:255]; // 256 palavras de 32 bits

    initial begin
        // Inicializa com instruções em BINÁRIO (convertidas do assembly)
        mem[0] = 32'b00000000000100000000000010110011;  // add x2, x0, x1
        mem[1] = 32'b00000000001000010000000100010011;  // sll x1, x2, x2
        mem[2] = 32'b00000000001100100000001000110011;  // xor x4, x2, x3
        mem[3] = 32'b11111111110000010000000110010011;  // addi x3, x2, -4
        mem[4] = 32'b00000000000000001010001010000011;  // lw x5, 0(x1)
        mem[5] = 32'b00000000010100010001001010100011;  // sw x5, 4(x2)
        mem[6] = 32'b00000000001000001000100001100011;  // bne x1, x2, 8
        mem[7] = 32'b00000000000000000000000000010011;  // nop (addi x0, x0, 0)
        mem[8] = 32'b00000000000000000000000000010011;  // nop (addi x0, x0, 0)
        mem[9] = 32'b00000000000000000000000000010011;  // nop (addi x0, x0, 0)
        mem[10] = 32'b00000000000100000000000001110011; // ebreak
        // Preencha o resto com zeros ou nops
        for (integer i = 11; i < 256; i = i + 1) begin
            mem[i] = 32'b00000000000000000000000000010011; // nop
        end
    end

    always @(*) begin
        instruction = mem[address[31:2]]; // Endereçamento word-aligned
    end

endmodule

riscv_core.v
`timescale 1ns / 1ps
// Instruções: lw, sw, add, xor, addi, sll, bne

module riscv_core (
    input wire clk,     // Clock
    input wire reset    // Reset
);

    // DECLARAÇÃO DE SINAIS INTERNOS
    // Estágio IF (Instruction Fetch)
    reg [31:0] PC;                      // Program Counter
    wire [31:0] PC_plus_4;              // PC + 4
    wire [31:0] PC_plus_imm;            // PC + immediate (para branch)
    wire [31:0] instruction;            // Instrução atual
    
    // Estágio ID (Instruction Decode)
    wire [6:0] opcode;                  // Bits [6:0] da instrução
    wire [4:0] rs1, rs2, rd;            // Campos dos registradores
    wire [2:0] funct3;                  // Bits [14:12]
    wire [6:0] funct7;                  // Bits [31:25]
    wire [31:0] imm_ext;                // Imediato estendido
    wire [31:0] read_data_1;            // Dado lido do registrador rs1
    wire [31:0] read_data_2;            // Dado lido do registrador rs2
    
    // Estágio EX (Execute)
    wire [31:0] alu_src_b;              // Segundo operando da ALU (MUX)
    wire [31:0] alu_result;             // Resultado da ALU
    wire alu_zero;                      // Flag zero da ALU
    wire [3:0] alu_control;             // Controle da ALU
    
    // Estágio MEM (Memory)
    wire [31:0] read_mem_data;          // Dado lido da memória
    
    // Estágio WB (Write Back)
    wire [31:0] write_back_data;        // Dado para writeback (MUX)
    
    // Sinais de Controle
    wire reg_write;            // Habilita escrita no registrador
    wire alu_src;              // ALU source
    wire mem_write;            // Habilita escrita na memória
    wire mem_to_reg;           // Habilita leitura da memória
    wire branch;               // Habilita branch
    wire branch_neq;          // Habilita branch não igual
    wire [1:0] alu_op;        // Operação da ALU
    wire PCSrc;               // Controle do MUX do PC

    // ATRIBUIÇÕES BÁSICAS
    assign opcode = instruction[6:0];          // Opcode da instrução
    assign rs1 = instruction[19:15];           // Registrador fonte 1
    assign rs2 = instruction[24:20];           // Registrador fonte 2
    assign rd = instruction[11:7];             // Registrador destino
    assign funct3 = instruction[14:12];       // Funct3
    assign funct7 = instruction[31:25];       // Funct7

    assign PC_plus_4 = PC + 4;                  // PC + 4
    assign PCSrc = (branch & alu_zero) | (branch_neq & ~alu_zero);   // Controle do MUX do PC

    // INSTANCIAÇÃO DOS MÓDULOS

    // Memória de Instruções (ROM)
    instruction_memory imem (
        .address(PC),                // Endereço da instrução
        .instruction(instruction)    // Saída da instrução
    );

    // Banco de Registradores
    register_file reg_file (
        .clk(clk),                    // Clock
        .reset(reset),                  // Reset
        .write_enable(reg_write),     // Habilita escrita
        .read_reg1(rs1),              // Registrador fonte 1
        .read_reg2(rs2),              // Registrador fonte 2
        .write_reg(rd),                // Registrador destino
        .write_data(write_back_data), // Dado a ser escrito
        .read_data1(read_data_1),     // Dado lido do registrador fonte 1
        .read_data2(read_data_2)      // Dado lido do registrador fonte 2
    );

    // Extensor de Imediato
    sign_extend sign_extend (
        .instruction(instruction),    // Instrução a ser estendida
        .imm_ext(imm_ext)             // Imediato estendido
    );

    // MUX para o operando B da ALU
    assign alu_src_b = alu_src ? imm_ext : read_data_2;    // Se alu_src for 1, usa imm_ext, senão usa read_data_2

    // Unidade de Controle Principal
    control_unit ctrl_unit (
        .opcode(opcode),           // Opcode da instrução
        .funct3(funct3),           // Funct3
        .funct7(funct7),           // Funct7
        .reg_write(reg_write),     // Habilita escrita
        .alu_src(alu_src),         // ALU source
        .mem_write(mem_write),     // Habilita escrita na memória
        .mem_to_reg(mem_to_reg),   // Habilita leitura da memória
        .branch(branch),           // Habilita branch
        .branch_neq(branch_neq),   // Habilita branch não igual
        .alu_op(alu_op)            // ALU operation
    );

    // Unidade de Controle da ALU
    alu_control_unit alu_ctrl (
        .alu_op(alu_op),         // ALU operation
        .funct3(funct3),         // Funct3
        .funct7(funct7),         // Funct7
        .alu_control(alu_control) // Controle da ALU
    );

    // ALU
    alu main_alu (
        .a(read_data_1),           // Operando A
        .b(alu_src_b),             // Operando B
        .alu_control(alu_control), // Controle da ALU
        .result(alu_result),       // Resultado da ALU
        .zero(alu_zero)           // Sinal de zero
    );

    // Cálculo do endereço de desvio
    assign PC_plus_imm = PC + imm_ext;     // PC + Imediato estendido

    // Memória de Dados
    data_memory dmem (
        .clk(clk),                    // Clock
        .mem_write(mem_write),       // Habilita escrita na memória
        .address(alu_result),        // Endereço da memória
        .write_data(read_data_2),   // Dado a ser escrito
        .read_data(read_mem_data)    // Dado lido da memória
    );

    // MUX para Write Back
    assign write_back_data = mem_to_reg ? read_mem_data : alu_result;   // Dados a serem escritos

    // LÓGICA DO PROGRAM COUNTER
    always @(posedge clk or posedge reset) begin
        if (reset) begin     // Reset do PC
            PC <= 32'b0;     // PC = 0
        end else begin       // Se não estiver em reset
            if (PCSrc) begin // Se o PCSrc for ativado
                PC <= PC_plus_imm;  // Desvio taken
            end else begin   // Se o PCSrc não for ativado
                PC <= PC_plus_4;    // Próxima instrução
            end
        end
    end

endmodule

riscv_tb.v
`timescale 1ns / 1ps

module riscv_tb;
    reg clk;
    reg reset;

    // Instanciação do processador
    riscv_core uut (
        .clk(clk),
        .reset(reset)
    );

    // Monitor para parar no ebreak
    always @(posedge clk) begin
        if (uut.instruction == 32'h00100073) begin
            $display("EBREAK encontrado! Parando simulação.");
            $display("Resultados finais:");
            for (integer i = 0; i < 32; i = i + 1) begin
                $display("x%0d = %b", i, uut.reg_file.registers[i]);
            end
            $finish;
        end
    end

    // Geração de clock (período de 10ns)
    always #5 clk = ~clk;

    // Procedimento de teste
    initial begin
        // Inicializa entradas
        clk = 0;
        reset = 1;

        // Dump de waveform
        $dumpfile("riscv_sim.vcd");
        $dumpvars(0, riscv_tb);

        // Monitor em tempo real
        $monitor("Time: %t | PC: %b | Instr: %b | ALU: a=%b b=%b res=%b",
                $time, uut.PC, uut.instruction,
                uut.read_data_1, uut.alu_src_b, uut.alu_result);

        // Reseta o processador
        #10;
        reset = 0;

        // DEBUG INICIAL
        #20;
        $display("=== DEBUG INICIAL ===");
        $display("PC = %b", uut.PC);
        $display("Instruction = %b", uut.instruction);
        $display("opcode = %b", uut.opcode);
        $display("funct3 = %b", uut.funct3);
        $display("reg_write = %b", uut.reg_write);
        $display("=== VALORES DOS REGISTRADORES ===");
        $display("x1 = %b", uut.reg_file.registers[1]);
        $display("x2 = %b", uut.reg_file.registers[2]);
        $display("x3 = %b", uut.reg_file.registers[3]);

        // DEBUG DA ALU CONTROL
        $display("=== DEBUG DA ALU CONTROL ===");
        $display("alu_op = %b", uut.alu_op);
        $display("funct3 = %b", uut.funct3);
        $display("funct7 = %b", uut.funct7);
        $display("alu_control = %b", uut.alu_control);

        // DEBUG DA LEITURA DE REGISTRADORES
        $display("=== DEBUG DA LEITURA DE REGISTRADORES ===");
        $display("rs1 = %d, rs2 = %d", uut.rs1, uut.rs2);
        $display("read_reg1 = %d, read_reg2 = %d", uut.reg_file.read_reg1, uut.reg_file.read_reg2);
        $display("read_data1 = %b, read_data2 = %b", uut.read_data_1, uut.read_data_2);
        $display("write_reg = %d, write_data = %b", uut.rd, uut.write_back_data);

        // Espera para executar algumas instruções
        #60;  // Espera mais 6 ciclos (total 8 ciclos desde o reset)

        $display("=== APÓS EXECUÇÃO ===");
        $display("PC = %b", uut.PC);
        $display("Instruction = %b", uut.instruction);
        $display("x1 = %b, x2 = %b, x3 = %b", 
                uut.reg_file.registers[1], 
                uut.reg_file.registers[2],
                uut.reg_file.registers[3]);

        // Final da simulação
        #10;
        $display("=== FINAL ===");
        $display("Final register values:");
        for (integer i = 0; i < 32; i = i + 1) begin
            $display("x%0d = %b", i, uut.reg_file.registers[i]);
        end

        // Espera para o EBREAK
        #200;

        // Se não encontrou ebreak, mostra mensagem
        $display("⚠️  EBREAK não foi encontrado. Parando simulação.");
        $display("Estado final:");
        for (integer i = 0; i < 32; i = i + 1) begin
            $display("x%0d = %b", i, uut.reg_file.registers[i]);
        end

        $finish;
    end

endmodule

riscv_sim.vcd
$date
	Tue Aug 26 22:44:35 2025
$end
$version
	Icarus Verilog
$end
$timescale
	1ps
$end
$scope module riscv_tb $end
$var reg 1 ! clk $end
$var reg 1 " reset $end
$scope module uut $end
$var wire 1 # PCSrc $end
$var wire 1 ! clk $end
$var wire 1 " reset $end
$var wire 32 $ write_back_data [31:0] $end
$var wire 5 % rs2 [4:0] $end
$var wire 5 & rs1 [4:0] $end
$var wire 1 ' reg_write $end
$var wire 32 ( read_mem_data [31:0] $end
$var wire 32 ) read_data_2 [31:0] $end
$var wire 32 * read_data_1 [31:0] $end
$var wire 5 + rd [4:0] $end
$var wire 7 , opcode [6:0] $end
$var wire 1 - mem_write $end
$var wire 1 . mem_to_reg $end
$var wire 32 / instruction [31:0] $end
$var wire 32 0 imm_ext [31:0] $end
$var wire 7 1 funct7 [6:0] $end
$var wire 3 2 funct3 [2:0] $end
$var wire 1 3 branch_neq $end
$var wire 1 4 branch $end
$var wire 1 5 alu_zero $end
$var wire 32 6 alu_src_b [31:0] $end
$var wire 1 7 alu_src $end
$var wire 32 8 alu_result [31:0] $end
$var wire 2 9 alu_op [1:0] $end
$var wire 4 : alu_control [3:0] $end
$var wire 32 ; PC_plus_imm [31:0] $end
$var wire 32 < PC_plus_4 [31:0] $end
$var reg 32 = PC [31:0] $end
$scope module alu_ctrl $end
$var wire 3 > funct3 [2:0] $end
$var wire 7 ? funct7 [6:0] $end
$var wire 2 @ alu_op [1:0] $end
$var reg 4 A alu_control [3:0] $end
$upscope $end
$scope module ctrl_unit $end
$var wire 3 B funct3 [2:0] $end
$var wire 7 C funct7 [6:0] $end
$var wire 7 D opcode [6:0] $end
$var parameter 7 E OPCODE_ADD_I $end
$var parameter 7 F OPCODE_BRANCH $end
$var parameter 7 G OPCODE_EBREAK $end
$var parameter 7 H OPCODE_LOAD $end
$var parameter 7 I OPCODE_R_TYPE $end
$var parameter 7 J OPCODE_STORE $end
$var reg 2 K alu_op [1:0] $end
$var reg 1 7 alu_src $end
$var reg 1 4 branch $end
$var reg 1 3 branch_neq $end
$var reg 1 . mem_to_reg $end
$var reg 1 - mem_write $end
$var reg 1 ' reg_write $end
$upscope $end
$scope module dmem $end
$var wire 1 ! clk $end
$var wire 1 - mem_write $end
$var wire 32 L write_data [31:0] $end
$var wire 32 M address [31:0] $end
$var reg 32 N read_data [31:0] $end
$scope begin $ivl_for_loop5 $end
$var integer 32 O i [31:0] $end
$upscope $end
$upscope $end
$scope module imem $end
$var wire 32 P address [31:0] $end
$var reg 32 Q instruction [31:0] $end
$scope begin $ivl_for_loop4 $end
$var integer 32 R i [31:0] $end
$upscope $end
$upscope $end
$scope module main_alu $end
$var wire 4 S alu_control [3:0] $end
$var wire 32 T b [31:0] $end
$var wire 1 5 zero $end
$var wire 32 U a [31:0] $end
$var reg 32 V result [31:0] $end
$upscope $end
$scope module reg_file $end
$var wire 1 ! clk $end
$var wire 5 W read_reg1 [4:0] $end
$var wire 5 X read_reg2 [4:0] $end
$var wire 1 " reset $end
$var wire 32 Y write_data [31:0] $end
$var wire 1 ' write_enable $end
$var wire 5 Z write_reg [4:0] $end
$var wire 32 [ read_data2 [31:0] $end
$var wire 32 \ read_data1 [31:0] $end
$scope begin $ivl_for_loop3 $end
$var integer 32 ] i [31:0] $end
$upscope $end
$upscope $end
$scope module sign_extend $end
$var wire 32 ^ instruction [31:0] $end
$var reg 32 _ imm_ext [31:0] $end
$upscope $end
$upscope $end
$scope begin $ivl_for_loop0 $end
$var integer 32 ` i [31:0] $end
$upscope $end
$scope begin $ivl_for_loop1 $end
$var integer 32 a i [31:0] $end
$upscope $end
$scope begin $ivl_for_loop2 $end
$var integer 32 b i [31:0] $end
$upscope $end
$upscope $end
$enddefinitions $end
$comment Show the parameter values. $end
$dumpall
b100011 J
b110011 I
b11 H
b1110011 G
b1100011 F
b10011 E
$end
#0
$dumpvars
bx b
bx a
bx `
b0 _
b100000000000010110011 ^
b100000 ]
b0 \
b0 [
b1 Z
b0 Y
b1 X
b0 W
b0 V
b0 U
b0 T
b0 S
b100000000 R
b100000000000010110011 Q
b0 P
b100000000 O
b101 N
b0 M
b0 L
b10 K
b110011 D
b0 C
b0 B
b0 A
b10 @
b0 ?
b0 >
b0 =
b100 <
b0 ;
b0 :
b10 9
b0 8
07
b0 6
15
04
03
b0 2
b0 1
b0 0
b100000000000010110011 /
0.
0-
b110011 ,
b1 +
b0 *
b0 )
b101 (
1'
b0 &
b1 %
b0 $
0#
1"
0!
$end
#5000
b100000 ]
1!
#10000
0!
0"
#15000
b10 $
b10 Y
05
b10 8
b10 M
b10 V
b10 6
b10 T
17
b0 9
b0 @
b0 K
1'
b10 0
b10 _
b10 +
b10 Z
b10 %
b10 X
b10 &
b10 W
b10011 ,
b10011 D
b1000010000000100010011 /
b1000010000000100010011 Q
b1000010000000100010011 ^
b1000 <
b110 ;
b100 =
b100 P
1!
#20000
0!
#25000
15
b0 $
b0 Y
b101 (
b101 N
b0 6
b0 T
b10 9
b10 @
b10 K
07
1'
b0 8
b0 M
b0 V
b0 0
b0 _
b100 +
b100 Z
b11 %
b11 X
b100 &
b100 W
b110011 ,
b110011 D
b0 *
b0 U
b0 \
b0 )
b0 L
b0 [
b1100100000001000110011 /
b1100100000001000110011 Q
b1100100000001000110011 ^
b1100 <
b1000 ;
b1000 =
b1000 P
1!
#30000
0!
#35000
b11111111111111111111111111111110 $
b11111111111111111111111111111110 Y
bx (
bx N
05
b11111111111111111111111111111110 8
b11111111111111111111111111111110 M
b11111111111111111111111111111110 V
b11111111111111111111111111111100 6
b11111111111111111111111111111100 T
b10 *
b10 U
b10 \
17
b0 9
b0 @
b0 K
1'
b11111111111111111111111111111100 0
b11111111111111111111111111111100 _
b1111111 1
b1111111 ?
b1111111 C
b11 +
b11 Z
b11100 %
b11100 X
b10 &
b10 W
b10011 ,
b10011 D
b11111111110000010000000110010011 /
b11111111110000010000000110010011 Q
b11111111110000010000000110010011 ^
b10000 <
b1000 ;
b1100 =
b1100 P
1!
#40000
0!
#45000
b101 (
b101 N
15
b0 8
b0 M
b0 V
b101 $
b101 Y
b0 6
b0 T
b0 *
b0 U
b0 \
1.
17
1'
b0 0
b0 _
b0 1
b0 ?
b0 C
b10 2
b10 >
b10 B
b101 +
b101 Z
b0 %
b0 X
b1 &
b1 W
b11 ,
b11 D
b1010001010000011 /
b1010001010000011 Q
b1010001010000011 ^
b10100 <
b10000 ;
b10000 =
b10000 P
1!
#50000
0!
#55000
b1010 (
b1010 N
05
b111 8
b111 M
b111 V
b0xx1x $
b0xx1x Y
b101 6
b101 T
b101 )
b101 L
b101 [
b10 *
b10 U
b10 \
1-
x.
17
0'
b101 0
b101 _
b1 2
b1 >
b1 B
b101 %
b101 X
b10 &
b10 W
b100011 ,
b100011 D
b10100010001001010100011 /
b10100010001001010100011 Q
b10100010001001010100011 ^
b11000 <
b11001 ;
b10100 =
b10100 P
1!
#60000
0!
#65000
b11111111111111111111111111111110 8
b11111111111111111111111111111110 M
b11111111111111111111111111111110 V
b10 6
b10 T
b1 :
b1 A
b1 S
b10 )
b10 L
b10 [
b0 *
b0 U
b0 \
14
b1 9
b1 @
b1 K
x.
0-
07
bx $
bx Y
b10000 0
b10000 _
b0 2
b0 >
b0 B
b10000 +
b10000 Z
b10 %
b10 X
b1 &
b1 W
b1100011 ,
b1100011 D
bx (
bx N
b1000001000100001100011 /
b1000001000100001100011 Q
b1000001000100001100011 ^
b11100 <
b101000 ;
b11000 =
b11000 P
1!
#70000
0!
#75000
b101 (
b101 N
15
b0 8
b0 M
b0 V
b0 6
b0 T
b0 :
b0 A
b0 S
b0 $
b0 Y
b0 )
b0 L
b0 [
17
1'
b0 9
b0 @
b0 K
04
0.
b0 0
b0 _
b0 +
b0 Z
b0 %
b0 X
b0 &
b0 W
b10011 ,
b10011 D
b10011 /
b10011 Q
b10011 ^
b100000 <
b11100 ;
b11100 =
b11100 P
1!
#80000
0!
#85000
b100100 <
b100000 ;
b100000 =
b100000 P
1!
#90000
0!
#95000
b101000 <
b100100 ;
b100100 =
b100100 P
1!
#100000
0!
b100000 a
#105000
07
0'
b1 %
b1 X
b1110011 ,
b1110011 D
b100000000000001110011 /
b100000000000001110011 Q
b100000000000001110011 ^
b101100 <
b101000 ;
b101000 =
b101000 P
1!
#110000
0!
#115000
17
1'
b0 %
b0 X
b10011 ,
b10011 D
b10011 /
b10011 Q
b10011 ^
b110000 <
b101100 ;
b101100 =
b101100 P
b100000 `
1!
